LICENSE
MANIFEST.in
README.md
RELEASE-VERSION
setup.py
version.py
rejester/__init__.py
rejester/_queue.py
rejester/_redis.py
rejester/_registry.py
rejester/_task_master.py
rejester/config.py
rejester/exceptions.py
rejester/run.py
rejester/run_multi_worker.py
rejester/workers.py
rejester.egg-info/PKG-INFO
rejester.egg-info/SOURCES.txt
rejester.egg-info/dependency_links.txt
rejester.egg-info/entry_points.txt
rejester.egg-info/not-zip-safe
rejester.egg-info/requires.txt
rejester.egg-info/top_level.txt
rejester/tests/__init__.py
rejester/tests/fixtures.py
rejester/tests/run.py
rejester/tests/test_cli.py
rejester/tests/test_dependencies.py
rejester/tests/test_queue.py
rejester/tests/test_registry.py
rejester/tests/test_task_master.py
rejester/tests/test_workers.py