Metadata-Version: 1.1
Name: rejester
Version: 0.8.1
Summary: redis-based python client library and command line tools for managing tasks executed by a group of configurable workers
Home-page: http://github.com/diffeo/rejester
Author: Diffeo, Inc.
Author-email: support@diffeo.com
License: MIT/X11 license http://opensource.org/licenses/MIT
Platform: UNKNOWN
Classifier: Development Status :: 3 - Alpha
Classifier: Topic :: Utilities
Classifier: License :: OSI Approved :: MIT License
